{
	"events": [
		{
			"character": "",
			"event_id": "dialogic_010",
			"options": [

			],
			"portrait": "",
			"question": "Where do you want to go?"
		},
		{
			"choice": "Work",
			"condition": "!=",
			"definition": "1653729061-648",
			"event_id": "dialogic_011",
			"value": "office"
		},
		{
			"definition": "1653729061-648",
			"event_id": "dialogic_014",
			"operation": "=",
			"random_upper_limit": 100,
			"set_random": false,
			"set_value": "office"
		},
		{
			"change_scene": "res://office.tscn",
			"event_id": "dialogic_041"
		},
		{
			"choice": "Home",
			"condition": "!=",
			"definition": "1653729061-648",
			"event_id": "dialogic_011",
			"value": "home"
		},
		{
			"definition": "1653729061-648",
			"event_id": "dialogic_014",
			"operation": "=",
			"random_upper_limit": 100,
			"set_random": false,
			"set_value": "home"
		},
		{
			"change_scene": "res://root.tscn",
			"event_id": "dialogic_041"
		},
		{
			"choice": "Cancel",
			"condition": "",
			"definition": "",
			"event_id": "dialogic_011",
			"value": ""
		},
		{
			"event_id": "dialogic_013"
		}
	],
	"metadata": {
		"dialogic-version": "1.4.1",
		"file": "timeline-1653691735.json",
		"name": "Elevator"
	}
}
